src/__init__.py
src/appears.py
src/client.py
src/exceptions.py
src/models.py
src/utils.py
src/appeears_client/__init__.py
src/appeears_client/auth.py
src/appeears_client/config.py
src/appeears_client/file_management.py
src/appeears_client/product_management.py
src/appeears_client/task_management.py
src/appeears_client/task_orchestrator.py
tests/__init__.py
tests/test_client.py
appears_api_client-0.1.2.dist-info/LICENSE
appears_api_client-0.1.2.dist-info/METADATA
appears_api_client-0.1.2.dist-info/WHEEL
appears_api_client-0.1.2.dist-info/top_level.txt
appears_api_client-0.1.2.dist-info/RECORD
